mitzasql/__init__.py
mitzasql/app.py
mitzasql/constants.py
mitzasql/history.py
mitzasql/logger.py
mitzasql/sessions_registry.py
mitzasql/state_machine.py
mitzasql/table_filter_parser.py
mitzasql/utils.py
mitzasql/version.py
mitzasql/autocomplete/__init__.py
mitzasql/autocomplete/context_detection.py
mitzasql/autocomplete/engine.py
mitzasql/autocomplete/smart_suggestions.py
mitzasql/db/__init__.py
mitzasql/db/connection.py
mitzasql/db/model.py
mitzasql/db/schema.py
mitzasql/db/schema_cache.py
mitzasql/sql_parser/__init__.py
mitzasql/sql_parser/ast.py
mitzasql/sql_parser/keywords.py
mitzasql/sql_parser/lexer.py
mitzasql/sql_parser/parser.py
mitzasql/sql_parser/parser_factory.py
mitzasql/sql_parser/state.py
mitzasql/sql_parser/tokens.py
mitzasql/sql_parser/parsers/__init__.py
mitzasql/sql_parser/parsers/call_stmt.py
mitzasql/sql_parser/parsers/delete_stmt.py
mitzasql/sql_parser/parsers/do_stmt.py
mitzasql/sql_parser/parsers/expression.py
mitzasql/sql_parser/parsers/insert_stmt.py
mitzasql/sql_parser/parsers/mixins.py
mitzasql/sql_parser/parsers/parser.py
mitzasql/sql_parser/parsers/replace_stmt.py
mitzasql/sql_parser/parsers/select_stmt.py
mitzasql/sql_parser/parsers/set_stmt.py
mitzasql/sql_parser/parsers/statement.py
mitzasql/sql_parser/parsers/update_stmt.py
mitzasql/ui/__init__.py
mitzasql/ui/builder.py
mitzasql/ui/clipboard.py
mitzasql/ui/main_loop.py
mitzasql/ui/syntax_highlight.py
mitzasql/ui/theme.py
mitzasql/ui/ui.py
mitzasql/ui/utils.py
mitzasql/ui/screens/__init__.py
mitzasql/ui/screens/base_widgets_factory.py
mitzasql/ui/screens/screen.py
mitzasql/ui/screens/session/__init__.py
mitzasql/ui/screens/session/session.py
mitzasql/ui/screens/session/states.py
mitzasql/ui/screens/session/widgets_factory.py
mitzasql/ui/screens/session_select/__init__.py
mitzasql/ui/screens/session_select/session_select.py
mitzasql/ui/screens/session_select/states.py
mitzasql/ui/screens/session_select/widgets_factory.py
mitzasql/ui/widgets/__init__.py
mitzasql-1.4.4.dist-info/LICENSE
mitzasql-1.4.4.dist-info/METADATA
mitzasql-1.4.4.dist-info/WHEEL
mitzasql-1.4.4.dist-info/top_level.txt
mitzasql-1.4.4.dist-info/RECORD
