Metadata-Version: 2.1
Name: mitzasql
Version: 1.4.4
Summary: Text user interface MySQL client
Home-page: https://github.com/vladbalmos/mitzasql
Author: Vlad Balmos
Author-email: vladbalmos@yahoo.com
License: MIT
Project-URL: Bug Tracker, https://github.com/vladbalmos/mitzasql/issues
Project-URL: Website, https://vladbalmos.github.io/mitzasql
Keywords: tui cli ncurses console mysql client
Platform: UNKNOWN
Classifier: Programming Language :: Python :: 3
Classifier: License :: OSI Approved :: MIT License
Classifier: Operating System :: POSIX :: Linux
Requires-Dist: appdirs (==1.4.4)
Requires-Dist: mysql-connector-python (==8.0.22)
Requires-Dist: pygments (==2.7.4)
Requires-Dist: urwid (==2.1.2)
Provides-Extra: clipboard
Requires-Dist: pyperclip (==1.8.1) ; extra == 'clipboard'
